[{"i":0,"n":"Ambriz","la":"-7.85740000","lo":"13.12510000","si":221,"s":"BGO","c":"AO"},{"i":1,"n":"Bula Atumba","la":"-7.31170000","lo":"14.31470000","si":221,"s":"BGO","c":"AO"},{"i":2,"n":"Caxito","la":"-8.57848000","lo":"13.66425000","si":221,"s":"BGO","c":"AO"},{"i":3,"n":"Dande","la":"-8.11330000","lo":"13.76520000","si":221,"s":"BGO","c":"AO"},{"i":4,"n":"Muxima","la":"-9.58790000","lo":"13.52510000","si":221,"s":"BGO","c":"AO"},{"i":5,"n":"Nambuangongo","la":"-8.56560000","lo":"13.65720000","si":221,"s":"BGO","c":"AO"},{"i":6,"n":"Pango Aluquém","la":"-8.55440000","lo":"13.58150000","si":221,"s":"BGO","c":"AO"},{"i":7,"n":"Úcua","la":"-8.67240000","lo":"13.68290000","si":221,"s":"BGO","c":"AO"},{"i":8,"n":"Baía Farta","la":"-12.57660000","lo":"13.47760000","si":218,"s":"BGU","c":"AO"},{"i":9,"n":"Balombo","la":"-12.90460000","lo":"13.59590000","si":218,"s":"BGU","c":"AO"},{"i":10,"n":"Benguela","la":"-12.57626000","lo":"13.40547000","si":218,"s":"BGU","c":"AO"},{"i":11,"n":"Bocoio","la":"-12.53030000","lo":"13.40420000","si":218,"s":"BGU","c":"AO"},{"i":12,"n":"Caimbambo","la":"-12.61330000","lo":"14.41940000","si":218,"s":"BGU","c":"AO"},{"i":13,"n":"Catumbela","la":"-12.43002000","lo":"13.54677000","si":218,"s":"BGU","c":"AO"},{"i":14,"n":"Chongoroi","la":"-12.78880000","lo":"13.79750000","si":218,"s":"BGU","c":"AO"},{"i":15,"n":"Cubal","la":"-12.58850000","lo":"14.42670000","si":218,"s":"BGU","c":"AO"},{"i":16,"n":"Ganda","la":"-12.68250000","lo":"14.42330000","si":218,"s":"BGU","c":"AO"},{"i":17,"n":"Lobito","la":"-12.36440000","lo":"13.53601000","si":218,"s":"BGU","c":"AO"},{"i":18,"n":"Sumbe","la":"-11.20610000","lo":"13.84480000","si":218,"s":"BGU","c":"AO"},{"i":19,"n":"Camacupa","la":"-12.01667000","lo":"17.48333000","si":212,"s":"BIE","c":"AO"},{"i":20,"n":"Catabola","la":"-12.15000000","lo":"17.28333000","si":212,"s":"BIE","c":"AO"},{"i":21,"n":"Chissamba","la":"-12.16667000","lo":"17.33333000","si":212,"s":"BIE","c":"AO"},{"i":22,"n":"Cuito","la":"-12.38333000","lo":"16.93333000","si":212,"s":"BIE","c":"AO"},{"i":23,"n":"Cabinda","la":"-5.55000000","lo":"12.20000000","si":228,"s":"CAB","c":"AO"},{"i":24,"n":"Menongue","la":"-14.65850000","lo":"17.69099000","si":226,"s":"CCU","c":"AO"},{"i":25,"n":"Quibala","la":"-10.73366000","lo":"14.97995000","si":216,"s":"CUS","c":"AO"},{"i":26,"n":"Sumbe","la":"-11.20605000","lo":"13.84371000","si":216,"s":"CUS","c":"AO"},{"i":27,"n":"Uacu Cungo","la":"-11.35669000","lo":"15.11719000","si":216,"s":"CUS","c":"AO"},{"i":28,"n":"Camabatela","la":"-8.18812000","lo":"15.37495000","si":217,"s":"CNO","c":"AO"},{"i":29,"n":"N’dalatando","la":"-9.29782000","lo":"14.91162000","si":217,"s":"CNO","c":"AO"},{"i":30,"n":"Ondjiva","la":"-17.06667000","lo":"15.73333000","si":215,"s":"CNN","c":"AO"},{"i":31,"n":"Caála","la":"-12.85250000","lo":"15.56056000","si":213,"s":"HUA","c":"AO"},{"i":32,"n":"Chela","la":"-12.30261000","lo":"15.43358000","si":213,"s":"HUA","c":"AO"},{"i":33,"n":"Huambo","la":"-12.77611000","lo":"15.73917000","si":213,"s":"HUA","c":"AO"},{"i":34,"n":"Longonjo","la":"-12.90667000","lo":"15.25333000","si":213,"s":"HUA","c":"AO"},{"i":35,"n":"Caconda","la":"-13.73333000","lo":"15.06667000","si":225,"s":"HUI","c":"AO"},{"i":36,"n":"Caluquembe","la":"-13.92093000","lo":"14.53476000","si":225,"s":"HUI","c":"AO"},{"i":37,"n":"Chibia","la":"-15.23657000","lo":"13.88468000","si":225,"s":"HUI","c":"AO"},{"i":38,"n":"Chicomba","la":"-14.30788000","lo":"14.98672000","si":225,"s":"HUI","c":"AO"},{"i":39,"n":"Chipindo","la":"-13.86830000","lo":"15.73277000","si":225,"s":"HUI","c":"AO"},{"i":40,"n":"Cuvango","la":"-14.27693000","lo":"16.31475000","si":225,"s":"HUI","c":"AO"},{"i":41,"n":"Gambos","la":"-15.80926000","lo":"14.07661000","si":225,"s":"HUI","c":"AO"},{"i":42,"n":"Humpata","la":"-15.07250000","lo":"13.36771000","si":225,"s":"HUI","c":"AO"},{"i":43,"n":"Jamba","la":"-14.76294000","lo":"15.83493000","si":225,"s":"HUI","c":"AO"},{"i":44,"n":"Lubango","la":"-14.91717000","lo":"13.49250000","si":225,"s":"HUI","c":"AO"},{"i":45,"n":"Matala","la":"-15.23967000","lo":"15.17246000","si":225,"s":"HUI","c":"AO"},{"i":46,"n":"Quilengues","la":"-13.99213000","lo":"13.76705000","si":225,"s":"HUI","c":"AO"},{"i":47,"n":"Quipungo","la":"-15.12203000","lo":"14.55953000","si":225,"s":"HUI","c":"AO"},{"i":48,"n":"Belas","la":"-9.06875000","lo":"13.16072000","si":222,"s":"LUA","c":"AO"},{"i":49,"n":"Cacuaco","la":"-8.82960000","lo":"13.29730000","si":222,"s":"LUA","c":"AO"},{"i":50,"n":"Cazenga","la":"-8.82860000","lo":"13.26650000","si":222,"s":"LUA","c":"AO"},{"i":51,"n":"Icolo e Bengo","la":"-9.24191000","lo":"13.73549000","si":222,"s":"LUA","c":"AO"},{"i":52,"n":"Luanda","la":"-8.83682000","lo":"13.23432000","si":222,"s":"LUA","c":"AO"},{"i":53,"n":"Talatona","la":"-8.89570000","lo":"13.19430000","si":222,"s":"LUA","c":"AO"},{"i":54,"n":"Viana","la":"-8.90210000","lo":"13.28610000","si":222,"s":"LUA","c":"AO"},{"i":55,"n":"Lucapa","la":"-8.68337000","lo":"20.27045000","si":223,"s":"LNO","c":"AO"},{"i":56,"n":"Cazaji","la":"-11.06715000","lo":"20.70148000","si":220,"s":"LSU","c":"AO"},{"i":57,"n":"Saurimo","la":"-9.66078000","lo":"20.39155000","si":220,"s":"LSU","c":"AO"},{"i":58,"n":"Malanje","la":"-9.54015000","lo":"16.34096000","si":227,"s":"MAL","c":"AO"},{"i":59,"n":"Léua","la":"-11.65000000","lo":"20.45000000","si":219,"s":"MOX","c":"AO"},{"i":60,"n":"Luau","la":"-10.70727000","lo":"22.22466000","si":219,"s":"MOX","c":"AO"},{"i":61,"n":"Luena","la":"-11.78333000","lo":"19.91667000","si":219,"s":"MOX","c":"AO"},{"i":62,"n":"Lumeje","la":"-11.55000000","lo":"20.78333000","si":219,"s":"MOX","c":"AO"},{"i":63,"n":"Bibala","la":"-14.93330000","lo":"13.68330000","si":5469,"s":"NAM","c":"AO"},{"i":64,"n":"Camucuio","la":"-15.45000000","lo":"12.88330000","si":5469,"s":"NAM","c":"AO"},{"i":65,"n":"Namibe","la":"-15.19670000","lo":"12.15220000","si":5469,"s":"NAM","c":"AO"},{"i":66,"n":"Tombua","la":"-15.78330000","lo":"11.86670000","si":5469,"s":"NAM","c":"AO"},{"i":67,"n":"Virei","la":"-14.46670000","lo":"13.26670000","si":5469,"s":"NAM","c":"AO"},{"i":68,"n":"Uíge","la":"-7.60874000","lo":"15.06131000","si":224,"s":"UIG","c":"AO"},{"i":69,"n":"Mbanza Congo","la":"-6.26703000","lo":"14.24010000","si":214,"s":"ZAI","c":"AO"},{"i":70,"n":"N'zeto","la":"-7.23116000","lo":"12.86660000","si":214,"s":"ZAI","c":"AO"},{"i":71,"n":"Soio","la":"-6.13490000","lo":"12.36894000","si":214,"s":"ZAI","c":"AO"}]