[{"i":0,"n":"Aketi","la":"2.73877000","lo":"23.78326000","si":2753,"s":"BU","c":"CD"},{"i":1,"n":"Bondo","la":"3.81461000","lo":"23.68665000","si":2753,"s":"BU","c":"CD"},{"i":2,"n":"Buta","la":"2.78582000","lo":"24.72997000","si":2753,"s":"BU","c":"CD"},{"i":3,"n":"Gemena","la":"3.25651000","lo":"19.77234000","si":2744,"s":"EQ","c":"CD"},{"i":4,"n":"Lisala","la":"2.15127000","lo":"21.51672000","si":2744,"s":"EQ","c":"CD"},{"i":5,"n":"Lukolela","la":"-1.06046000","lo":"17.18210000","si":2744,"s":"EQ","c":"CD"},{"i":6,"n":"Mbandaka","la":"0.04865000","lo":"18.26034000","si":2744,"s":"EQ","c":"CD"},{"i":7,"n":"Likasi","la":"-10.98303000","lo":"26.73840000","si":2750,"s":"HK","c":"CD"},{"i":8,"n":"Lubumbashi","la":"-11.66089000","lo":"27.47938000","si":2750,"s":"HK","c":"CD"},{"i":9,"n":"Bukama","la":"-9.20443000","lo":"25.85475000","si":2758,"s":"HL","c":"CD"},{"i":10,"n":"Kamina","la":"-8.73508000","lo":"24.99798000","si":2758,"s":"HL","c":"CD"},{"i":11,"n":"Isiro","la":"2.77391000","lo":"27.61603000","si":2734,"s":"HU","c":"CD"},{"i":12,"n":"Wamba","la":"2.14838000","lo":"27.99466000","si":2734,"s":"HU","c":"CD"},{"i":13,"n":"Watsa","la":"3.03716000","lo":"29.53551000","si":2734,"s":"HU","c":"CD"},{"i":14,"n":"Bunia","la":"1.55941000","lo":"30.25224000","si":2751,"s":"IT","c":"CD"},{"i":15,"n":"Ilebo","la":"-4.33111000","lo":"20.58638000","si":2757,"s":"KS","c":"CD"},{"i":16,"n":"Luebo","la":"-5.35218000","lo":"21.42192000","si":2757,"s":"KS","c":"CD"},{"i":17,"n":"Mweka","la":"-4.85187000","lo":"21.55950000","si":2757,"s":"KS","c":"CD"},{"i":18,"n":"Tshikapa","la":"-6.41621000","lo":"20.79995000","si":2757,"s":"KS","c":"CD"},{"i":19,"n":"Gandajika","la":"-6.74504000","lo":"23.95328000","si":2735,"s":"KE","c":"CD"},{"i":20,"n":"Kabinda","la":"-6.13791000","lo":"24.48179000","si":2735,"s":"KE","c":"CD"},{"i":21,"n":"Mbuji-Mayi","la":"-6.13603000","lo":"23.58979000","si":2735,"s":"KE","c":"CD"},{"i":22,"n":"Kinshasa","la":"-4.32758000","lo":"15.31357000","si":2741,"s":"KN","c":"CD"},{"i":23,"n":"Boma","la":"-5.85098000","lo":"13.05364000","si":2746,"s":"BC","c":"CD"},{"i":24,"n":"Kasangulu","la":"-4.58330000","lo":"15.16554000","si":2746,"s":"BC","c":"CD"},{"i":25,"n":"Matadi","la":"-5.83861000","lo":"13.46306000","si":2746,"s":"BC","c":"CD"},{"i":26,"n":"Mbanza-Ngungu","la":"-5.25837000","lo":"14.85838000","si":2746,"s":"BC","c":"CD"},{"i":27,"n":"Moanda","la":"-5.92753000","lo":"12.37148000","si":2746,"s":"BC","c":"CD"},{"i":28,"n":"Tshela","la":"-4.99707000","lo":"12.94840000","si":2746,"s":"BC","c":"CD"},{"i":29,"n":"Kasongo-Lunda","la":"-6.47833000","lo":"16.81735000","si":2740,"s":"KG","c":"CD"},{"i":30,"n":"Bandundu","la":"-3.31687000","lo":"17.38063000","si":2759,"s":"KL","c":"CD"},{"i":31,"n":"Bulungu","la":"-4.54437000","lo":"18.60364000","si":2759,"s":"KL","c":"CD"},{"i":32,"n":"Kikwit","la":"-5.04098000","lo":"18.81619000","si":2759,"s":"KL","c":"CD"},{"i":33,"n":"Mangai","la":"-4.02328000","lo":"19.53385000","si":2759,"s":"KL","c":"CD"},{"i":34,"n":"Lubao","la":"-5.38771000","lo":"25.74885000","si":2747,"s":"LO","c":"CD"},{"i":35,"n":"Mwene-Ditu","la":"-7.00906000","lo":"23.45278000","si":2747,"s":"LO","c":"CD"},{"i":36,"n":"Kasaji","la":"-10.38342000","lo":"23.44987000","si":4953,"s":"LU","c":"CD"},{"i":37,"n":"Kolwezi","la":"-10.71666700","lo":"25.46666700","si":4953,"s":"LU","c":"CD"},{"i":38,"n":"Bolobo","la":"-2.15800000","lo":"16.23249000","si":2755,"s":"MN","c":"CD"},{"i":39,"n":"Inongo","la":"-1.92750000","lo":"18.28810000","si":2755,"s":"MN","c":"CD"},{"i":40,"n":"Mushie","la":"-3.01728000","lo":"16.92238000","si":2755,"s":"MN","c":"CD"},{"i":41,"n":"Nioki","la":"-2.72037000","lo":"17.69001000","si":2755,"s":"MN","c":"CD"},{"i":42,"n":"Kampene","la":"-3.59678000","lo":"26.66715000","si":2745,"s":"MA","c":"CD"},{"i":43,"n":"Kasongo","la":"-4.42741000","lo":"26.66656000","si":2745,"s":"MA","c":"CD"},{"i":44,"n":"Kindu","la":"-2.94373000","lo":"25.92237000","si":2745,"s":"MA","c":"CD"},{"i":45,"n":"Bumba","la":"2.18771000","lo":"22.46827000","si":2752,"s":"MO","c":"CD"},{"i":46,"n":"Beni","la":"0.49113000","lo":"29.47306000","si":2749,"s":"NK","c":"CD"},{"i":47,"n":"Butembo","la":"0.14164000","lo":"29.29117000","si":2749,"s":"NK","c":"CD"},{"i":48,"n":"Goma","la":"-1.67409000","lo":"29.22845000","si":2749,"s":"NK","c":"CD"},{"i":49,"n":"Sake","la":"-1.57386000","lo":"29.04339000","si":2749,"s":"NK","c":"CD"},{"i":50,"n":"Bosobolo","la":"4.18980000","lo":"19.88330000","si":2739,"s":"NU","c":"CD"},{"i":51,"n":"Businga","la":"3.33863000","lo":"20.88577000","si":2739,"s":"NU","c":"CD"},{"i":52,"n":"Gbadolite","la":"4.27900000","lo":"21.00284000","si":2739,"s":"NU","c":"CD"},{"i":53,"n":"Lodja","la":"-3.52105000","lo":"23.60050000","si":2743,"s":"SA","c":"CD"},{"i":54,"n":"Lusambo","la":"-4.97503000","lo":"23.44391000","si":2743,"s":"SA","c":"CD"},{"i":55,"n":"Bukavu","la":"-2.49077000","lo":"28.84281000","si":2738,"s":"SK","c":"CD"},{"i":56,"n":"Kabare","la":"-2.49682000","lo":"28.79081000","si":2738,"s":"SK","c":"CD"},{"i":57,"n":"Uvira","la":"-3.39534000","lo":"29.13779000","si":2738,"s":"SK","c":"CD"},{"i":58,"n":"Bongandanga","la":"1.50695000","lo":"21.07260000","si":2748,"s":"SU","c":"CD"},{"i":59,"n":"Libenge","la":"3.65332000","lo":"18.63566000","si":2748,"s":"SU","c":"CD"},{"i":60,"n":"Kabalo","la":"-6.05255000","lo":"26.91430000","si":2733,"s":"TA","c":"CD"},{"i":61,"n":"Kalemie","la":"-5.94749000","lo":"29.19471000","si":2733,"s":"TA","c":"CD"},{"i":62,"n":"Kongolo","la":"-5.38532000","lo":"27.00029000","si":2733,"s":"TA","c":"CD"},{"i":63,"n":"Basoko","la":"1.23909000","lo":"23.61598000","si":2756,"s":"TO","c":"CD"},{"i":64,"n":"Kisangani","la":"0.51528000","lo":"25.19099000","si":2756,"s":"TO","c":"CD"},{"i":65,"n":"Yangambi","la":"0.76755000","lo":"24.43973000","si":2756,"s":"TO","c":"CD"},{"i":66,"n":"Boende","la":"-0.28163000","lo":"20.88053000","si":2732,"s":"TU","c":"CD"}]