[{"i":23,"n":"Andrijevica","i2":"01","c":"ME"},{"i":13,"n":"Bar","i2":"02","c":"ME"},{"i":21,"n":"Berane","i2":"03","c":"ME"},{"i":25,"n":"Bijelo Polje","i2":"04","c":"ME"},{"i":30,"n":"Budva","i2":"05","c":"ME"},{"i":14,"n":"Danilovgrad","i2":"07","c":"ME"},{"i":24,"n":"Gusinje","i2":"22","c":"ME"},{"i":5682,"n":"Herceg-Novi","i2":"08","c":"ME"},{"i":31,"n":"Kolašin","i2":"09","c":"ME"},{"i":26,"n":"Kotor","i2":"10","c":"ME"},{"i":22,"n":"Mojkovac","i2":"11","c":"ME"},{"i":17,"n":"Nikšić","i2":"12","c":"ME"},{"i":28,"n":"Old Royal Capital Cetinje","i2":"06","c":"ME"},{"i":12,"n":"Petnjica","i2":"23","c":"ME"},{"i":19,"n":"Plav","i2":"13","c":"ME"},{"i":20,"n":"Pljevlja","i2":"14","c":"ME"},{"i":16,"n":"Plužine","i2":"15","c":"ME"},{"i":27,"n":"Podgorica","i2":"16","c":"ME"},{"i":15,"n":"Rožaje","i2":"17","c":"ME"},{"i":18,"n":"Šavnik","i2":"18","c":"ME"},{"i":29,"n":"Tivat","i2":"19","c":"ME"},{"i":5683,"n":"Tuzi","i2":"24","c":"ME"},{"i":33,"n":"Ulcinj","i2":"20","c":"ME"},{"i":32,"n":"Žabljak","i2":"21","c":"ME"},{"i":5684,"n":"Zeta","i2":"25","c":"ME"}]