[{"i":1973,"n":"Arkhangai","i2":"073","c":"MN"},{"i":1969,"n":"Bayan-Ölgii","i2":"071","c":"MN"},{"i":1976,"n":"Bayankhongor","i2":"069","c":"MN"},{"i":1961,"n":"Bulgan","i2":"067","c":"MN"},{"i":1962,"n":"Darkhan-Uul","i2":"037","c":"MN"},{"i":1963,"n":"Dornod","i2":"061","c":"MN"},{"i":1981,"n":"Dornogovi","i2":"063","c":"MN"},{"i":1970,"n":"Dundgovi","i2":"059","c":"MN"},{"i":1972,"n":"Govi-Altai","i2":"065","c":"MN"},{"i":1978,"n":"Govisümber","i2":"064","c":"MN"},{"i":1974,"n":"Khentii","i2":"039","c":"MN"},{"i":1964,"n":"Khovd","i2":"043","c":"MN"},{"i":1975,"n":"Khövsgöl","i2":"041","c":"MN"},{"i":1967,"n":"Ömnögovi","i2":"053","c":"MN"},{"i":1966,"n":"Orkhon","i2":"035","c":"MN"},{"i":1965,"n":"Övörkhangai","i2":"055","c":"MN"},{"i":1980,"n":"Selenge","i2":"049","c":"MN"},{"i":1977,"n":"Sükhbaatar","i2":"051","c":"MN"},{"i":1968,"n":"Töv","i2":"047","c":"MN"},{"i":5453,"n":"Ulaanbaatar","i2":"001","c":"MN"},{"i":1971,"n":"Uvs","i2":"046","c":"MN"},{"i":1979,"n":"Zavkhan","i2":"057","c":"MN"}]